pythainer/__init__.py
pythainer/cli.py
pythainer/sysutils.py
pythainer/builders/__init__.py
pythainer/builders/cmds.py
pythainer/builders/contexts.py
pythainer/builders/utils.py
pythainer/builders/commands/__init__.py
pythainer/builders/commands/run/__init__.py
pythainer/builders/commands/run/mounts.py
pythainer/examples/__init__.py
pythainer/examples/builders/__init__.py
pythainer/examples/installs/__init__.py
pythainer/examples/runners/__init__.py
pythainer/runners/__init__.py
pythainer-0.0.6.dist-info/METADATA
pythainer-0.0.6.dist-info/WHEEL
pythainer-0.0.6.dist-info/entry_points.txt
pythainer-0.0.6.dist-info/licenses/LICENSE
pythainer-0.0.6.dist-info/RECORD
