Metadata-Version: 2.4
Name: pythainer
Version: 0.0.6
Summary: A pythonic toolkit for composing, managing, and deploying Docker images and containers.
Project-URL: Homepage, https://github.com/apaolillo/pythainer
Project-URL: Issues, https://github.com/apaolillo/pythainer/issues
Author-email: Antonio Paolillo <antonio@paolillo.be>
License-File: LICENSE
Classifier: License :: OSI Approved :: MIT License
Classifier: Operating System :: OS Independent
Classifier: Programming Language :: Python :: 3
Requires-Python: >=3.10
Requires-Dist: black<=25.1.0
Requires-Dist: click<=8.2.1
Requires-Dist: isort<=6.0.1
Provides-Extra: dev
Requires-Dist: mypy<=1.18.1; extra == 'dev'
Requires-Dist: ruff<=0.13.0; extra == 'dev'
Requires-Dist: types-click<=7.1.8; extra == 'dev'
Provides-Extra: test
Requires-Dist: pytest-cov>=4; extra == 'test'
Requires-Dist: pytest>=8; extra == 'test'
